README.md
setup.cfg
setup.py
rw_dynamicworld_cd.egg-info/PKG-INFO
rw_dynamicworld_cd.egg-info/SOURCES.txt
rw_dynamicworld_cd.egg-info/dependency_links.txt
rw_dynamicworld_cd.egg-info/top_level.txt
wri_change_detection/__init__.py
wri_change_detection/gee_classifier.py
wri_change_detection/post_classification_filters.py
wri_change_detection/preprocessing.py