Metadata-Version: 2.1
Name: rw-dynamicworld-cd
Version: 0.0.1
Summary: A series of Python modules for performing change detection and post-classification processing for the Dynamic World land cover product.
Home-page: https://github.com/wri/rw-dynamicworld-cd
Author: Kristine Lister and Alex Kovac
Author-email: kristine.lister@wri.org
License: UNKNOWN
Platform: UNKNOWN
Classifier: Programming Language :: Python :: 3
Classifier: License :: OSI Approved :: MIT License
Classifier: Operating System :: OS Independent
Requires-Python: >=3.6
